postponed/__init__.py
postponed/postponed.py
postponed-0.0.1.dist-info/LICENSE
postponed-0.0.1.dist-info/METADATA
postponed-0.0.1.dist-info/WHEEL
postponed-0.0.1.dist-info/top_level.txt
postponed-0.0.1.dist-info/RECORD
