Metadata-Version: 2.1
Name: postponed
Version: 0.0.1
Summary: Module to postpone the execution of a function.
Author: Martin de La Gorce
Author-email: martin.delagorce@gmail.com
License: MIT
License-File: LICENSE
Requires-Dist: typeguard
